akshare_api/__init__.py
akshare_api/cli.py
akshare_api/service_manager.py
akshare_api-1.1.0.dist-info/licenses/LICENSE
akshare_api-1.1.0.dist-info/METADATA
akshare_api-1.1.0.dist-info/WHEEL
akshare_api-1.1.0.dist-info/entry_points.txt
akshare_api-1.1.0.dist-info/top_level.txt
akshare_api-1.1.0.dist-info/RECORD
