Metadata-Version: 2.4
Name: akshare-api
Version: 1.1.0
Summary: 基于AKTools公开API的AKShare股票数据接口Python调用库
Home-page: https://github.com/JoshuaMaoJH/akshare-api
Author: JMTechPower
Author-email: JMTechPower <joshua.maojh@gmail.com>
Maintainer: JMTechPower
Maintainer-email: JMTechPower <joshua.maojh@gmail.com>
License-Expression: MIT
Project-URL: Homepage, https://github.com/JoshuaMaoJH/akshare-api
Project-URL: Documentation, https://github.com/JoshuaMaoJH/akshare-api#readme
Project-URL: Repository, https://github.com/JoshuaMaoJH/akshare-api.git
Project-URL: Bug Tracker, https://github.com/JoshuaMaoJH/akshare-api/issues
Project-URL: Changelog, https://github.com/JoshuaMaoJH/akshare-api/blob/main/CHANGELOG.md
Keywords: akshare,stock,finance,api,data,trading,china,market
Classifier: Development Status :: 5 - Production/Stable
Classifier: Intended Audience :: Developers
Classifier: Intended Audience :: Financial and Insurance Industry
Classifier: Operating System :: OS Independent
Classifier: Programming Language :: Python :: 3
Classifier: Programming Language :: Python :: 3.7
Classifier: Programming Language :: Python :: 3.8
Classifier: Programming Language :: Python :: 3.9
Classifier: Programming Language :: Python :: 3.10
Classifier: Programming Language :: Python :: 3.11
Classifier: Programming Language :: Python :: 3.12
Classifier: Topic :: Office/Business :: Financial :: Investment
Classifier: Topic :: Software Development :: Libraries :: Python Modules
Requires-Python: >=3.7
License-File: LICENSE
Requires-Dist: requests>=2.25.0
Requires-Dist: pandas>=1.3.0
Requires-Dist: numpy>=1.20.0
Requires-Dist: aktools>=1.0.0
Provides-Extra: dev
Requires-Dist: pytest>=6.0; extra == "dev"
Requires-Dist: pytest-cov>=2.0; extra == "dev"
Requires-Dist: black>=21.0; extra == "dev"
Requires-Dist: flake8>=3.8; extra == "dev"
Requires-Dist: mypy>=0.800; extra == "dev"
Requires-Dist: sphinx>=4.0; extra == "dev"
Requires-Dist: sphinx-rtd-theme>=0.5; extra == "dev"
Provides-Extra: docs
Requires-Dist: sphinx>=4.0; extra == "docs"
Requires-Dist: sphinx-rtd-theme>=0.5; extra == "docs"
Requires-Dist: myst-parser>=0.15; extra == "docs"
Dynamic: author
Dynamic: home-page
Dynamic: license-file
Dynamic: maintainer
Dynamic: requires-python
